{
    "Yendri Tellez":"Receptor",
    "Jorge Álvarez":"Receptor",
    "Julio César Noguera":"Receptor",
    "Leonel Segura":"Jugador de Cuadro",
    "Pedro Smith":"Jugador de Cuadro",
    "Humberto Bravo":"Jugador de Cuadro",
    "Eglis Eugelles Antunez":"Jugador de Cuadro",
    "Alexander Ayala":"Jugador de Cuadro",
    "Yandy Yanes":"Jugador de Cuadro",
    "Yosbel Pérez":"Jugador de Cuadro",
    "Marino Luis":"Jugador de Cuadro",
    "Leonel Moas (hijo)":"Jardinero",
    "Loidel Chapelli (hijo)":"Jardinero",
    "Danny Luaces":"Jardinero",
    "Luis González Azcuy":"Jardinero",
    "Jorge Cardosa":"Jardinero",
    "Yanmichel Flores":"Jardinero",
    "Yoel Darce":"Jardinero",
    "Yariel Rodríguez Yordy":"Lanzador",
    "Yosimar Cousín":"Lanzador",
    "Dariel Góngora De La Torre":"Lanzador",
    "Juan Sebastian Contreras":"Lanzador",
    "Erisleri Basulto":"Lanzador",
    "Vicyohandri Odelín":"Lanzador",
    "Carlos Espinosa":"Lanzador",
    "Roger Trenchs":"Lanzador",
    "Carlos Alfredo Pérez Vergara":"Lanzador",
    "Frank Madan":"Lanzador",
    "Lisander Hernández":"Lanzador",
    "Ramón Robles":"Lanzador",
    "Jose Ramon Rodríguez Menéndez":"Lanzador",
    "Ángel Ramírez":"Lanzador",
    "Miguel Borroto":"Director"

}








